cdk_aws_iotfleetwise/__init__.py
cdk_aws_iotfleetwise/py.typed
cdk_aws_iotfleetwise/_jsii/__init__.py
cdk_aws_iotfleetwise/_jsii/cdk-aws-iotfleetwise@0.3.7.jsii.tgz
cdk_aws_iotfleetwise-0.3.7.dist-info/LICENSE
cdk_aws_iotfleetwise-0.3.7.dist-info/METADATA
cdk_aws_iotfleetwise-0.3.7.dist-info/NOTICE
cdk_aws_iotfleetwise-0.3.7.dist-info/WHEEL
cdk_aws_iotfleetwise-0.3.7.dist-info/top_level.txt
cdk_aws_iotfleetwise-0.3.7.dist-info/RECORD
