Metadata-Version: 2.1
Name: cdk-aws-iotfleetwise
Version: 0.3.7
Summary: L2 CDK construct to provision AWS IoT Fleetwise
Home-page: https://github.com/aws-samples/cdk-aws-iotfleetwise.git
Author: Francesco Salamida<salamida@amazon.com>
License: MIT-0
Project-URL: Source, https://github.com/aws-samples/cdk-aws-iotfleetwise.git
Classifier: Intended Audience :: Developers
Classifier: Operating System :: OS Independent
Classifier: Programming Language :: JavaScript
Classifier: Programming Language :: Python :: 3 :: Only
Classifier: Programming Language :: Python :: 3.8
Classifier: Programming Language :: Python :: 3.9
Classifier: Programming Language :: Python :: 3.10
Classifier: Programming Language :: Python :: 3.11
Classifier: Typing :: Typed
Classifier: Development Status :: 5 - Production/Stable
Classifier: License :: OSI Approved
Requires-Python: ~=3.8
License-File: LICENSE
License-File: NOTICE
Requires-Dist: aws-cdk-lib <3.0.0,>=2.96.2
Requires-Dist: constructs <11.0.0,>=10.0.5
Requires-Dist: jsii <2.0.0,>=1.98.0
Requires-Dist: publication >=0.0.3
Requires-Dist: typeguard ~=2.13.3
